okreport.py
python_okreport-1.1.0.dist-info/METADATA
python_okreport-1.1.0.dist-info/WHEEL
python_okreport-1.1.0.dist-info/top_level.txt
python_okreport-1.1.0.dist-info/RECORD
