Metadata-Version: 2.1
Name: python-okreport
Version: 1.1.0
Summary: simple report automatic rendering
Home-page: https://github.com/lawley0316/okreport
Author: Lawley
Author-email: lawley0316@gmail.com
License: MIT
Classifier: License :: OSI Approved :: MIT License
Classifier: Programming Language :: Python
Classifier: Programming Language :: Python :: 3
Classifier: Programming Language :: Python :: 3.6
Classifier: Programming Language :: Python :: Implementation :: CPython
Classifier: Programming Language :: Python :: Implementation :: PyPy
Requires-Python: >=3.6.0
Requires-Dist: jinja2
